Metadata-Version: 2.1
Name: github-full-backup
Version: 0.1.0
Summary: A library to backup your GitHubs.
Home-page: https://github.com/onuratakan/GitHub-Backup
Author: Onur Atakan ULUSOY
Author-email: atadogan06@gmail.com
License: MIT
Platform: UNKNOWN
Requires-Python: >= 3
License-File: LICENSE
